Calculator_Raj-1.1.1.dist-info/METADATA
Calculator_Raj-1.1.1.dist-info/RECORD
Calculator_Raj-1.1.1.dist-info/WHEEL
Calculator_Raj-1.1.1.dist-info/entry_points.txt
Calculator_Raj-1.1.1.dist-info/top_level.txt
calci_raj/__init__.py
calci_raj/topsis.py
