Metadata-Version: 2.1
Name: Calculator-Raj
Version: 1.1.1
Summary: This is a simple calculator program
Home-page: https://test.pypi.org/legacy/
Author: Rajeev Singla
Author-email: UNKNOWN
License: UNKNOWN
Platform: UNKNOWN
Classifier: License :: OSI Approved :: MIT License
Classifier: Programming Language :: Python :: 3
Classifier: Programming Language :: Python :: 3.7
